PopulationCoding/__init__.py
PopulationCoding/corr.py
PopulationCoding/dimred.py
PopulationCoding/info.py
PopulationCoding/predict.py
PopulationCoding/utils.py
PopulationCoding-0.1.1.dist-info/LICENSE.md
PopulationCoding-0.1.1.dist-info/METADATA
PopulationCoding-0.1.1.dist-info/WHEEL
PopulationCoding-0.1.1.dist-info/top_level.txt
PopulationCoding-0.1.1.dist-info/RECORD
