Metadata-Version: 2.1
Name: PopulationCoding
Version: 0.1.1
Summary: Tools for analyzing dynamics and encoding in neural populations
Author-email: Jason Manley <jmanley@rockefeller.edu>
License: GNU GENERAL PUBLIC LICENSE
Project-URL: Homepage, https://github.com/vazirilab/scaling_analysis/tree/main/PopulationCoding
Project-URL: Documentation, https://scaling-analysis.readthedocs.io/projects/PopulationCoding
Project-URL: Issues, https://github.com/vazirilab/scaling_analysis/issues
Classifier: Programming Language :: Python :: 3
Classifier: License :: OSI Approved :: GNU General Public License v3 (GPLv3)
Requires-Python: >=3.8
License-File: LICENSE.md
Requires-Dist: matplotlib
Requires-Dist: numpy
Requires-Dist: scikit-learn
Requires-Dist: scipy
